amsdal_cli/Third-Party Materials - AMSDAL Dependencies - License Notices.md
amsdal_cli/__about__.py
amsdal_cli/__init__.py
amsdal_cli/app.py
amsdal_cli/main.py
amsdal_cli/py.typed
amsdal_cli/commands/__init__.py
amsdal_cli/commands/callbacks.py
amsdal_cli/commands/api_check/__init__.py
amsdal_cli/commands/api_check/command.py
amsdal_cli/commands/api_check/config.py
amsdal_cli/commands/api_check/data_classes.py
amsdal_cli/commands/api_check/operation_log.py
amsdal_cli/commands/api_check/services/__init__.py
amsdal_cli/commands/api_check/services/comparison.py
amsdal_cli/commands/api_check/services/data_factory.py
amsdal_cli/commands/api_check/services/loader.py
amsdal_cli/commands/api_check/services/runner.py
amsdal_cli/commands/api_check/services/storage.py
amsdal_cli/commands/build/__init__.py
amsdal_cli/commands/build/command.py
amsdal_cli/commands/build/constants.py
amsdal_cli/commands/build/schemas/__init__.py
amsdal_cli/commands/build/schemas/schema_json_loader.py
amsdal_cli/commands/build/schemas/data_models/__init__.py
amsdal_cli/commands/build/schemas/data_models/custom_code.py
amsdal_cli/commands/build/schemas/data_models/options.py
amsdal_cli/commands/build/schemas/data_models/schemas_directory.py
amsdal_cli/commands/build/schemas/extenders/__init__.py
amsdal_cli/commands/build/schemas/extenders/custom_code_extender.py
amsdal_cli/commands/build/schemas/extenders/options_extender.py
amsdal_cli/commands/build/schemas/loaders/__init__.py
amsdal_cli/commands/build/schemas/loaders/base.py
amsdal_cli/commands/build/schemas/loaders/cli_custom_code_loader.py
amsdal_cli/commands/build/schemas/loaders/cli_loader.py
amsdal_cli/commands/build/schemas/loaders/cli_options_loader.py
amsdal_cli/commands/build/schemas/loaders/cli_statics_loader.py
amsdal_cli/commands/build/schemas/loaders/cli_transactions_loader.py
amsdal_cli/commands/build/schemas/loaders/utils.py
amsdal_cli/commands/build/schemas/mixins/__init__.py
amsdal_cli-0.5.10.dist-info/METADATA
amsdal_cli-0.5.10.dist-info/WHEEL
amsdal_cli-0.5.10.dist-info/entry_points.txt
amsdal_cli-0.5.10.dist-info/licenses/LICENSE.txt
amsdal_cli-0.5.10.dist-info/RECORD
