Metadata-Version: 2.4
Name: amsdal_cli
Version: 0.5.10
Summary: CLI for AMSDAL framework
Project-URL: Documentation, https://pypi.org/project/amsdal_cli/#readme
Project-URL: Issues, https://pypi.org/project/amsdal_cli/
Project-URL: Source, https://pypi.org/project/amsdal_cli/
Author-email: "A. Michael Salem" <ams@amsdal.com>
License: AMSDAL End User License Agreement
License-File: LICENSE.txt
Classifier: Development Status :: 4 - Beta
Classifier: Programming Language :: Python
Classifier: Programming Language :: Python :: 3.11
Classifier: Programming Language :: Python :: 3.12
Classifier: Programming Language :: Python :: 3.13
Classifier: Programming Language :: Python :: Implementation :: CPython
Classifier: Programming Language :: Python :: Implementation :: PyPy
Requires-Python: <3.14,>=3.11
Requires-Dist: amsdal-server==0.5.*
Requires-Dist: click<8.2.0
Requires-Dist: faker==27.*
Requires-Dist: gitpython~=3.1
Requires-Dist: httpx==0.28.*
Requires-Dist: jinja2~=3.1
Requires-Dist: pydantic-settings~=2.12
Requires-Dist: pydantic~=2.12
Requires-Dist: rich~=14.0
Requires-Dist: typer~=0.15.3
Requires-Dist: watchfiles~=0.21
